src/__init__.py
src/cmd.py
src/cleaner/__init__.py
src/cleaner/cleaner.py
src/cleaner/cleaner_cmd.py
src/cleaner/utils.py
src/file_handler/__init__.py
src/file_handler/fileHandler.py
src/file_handler/fileHandler_cmd.py
src/file_handler/utils.py
src/reporter/__init__.py
src/reporter/reporter.py
src/reporter/reporter_cmd.py
src/reporter/utils.py
src/transformer/__init__.py
src/transformer/transformer.py
src/transformer/transformer_cmd.py
src/transformer/utils.py
src/utils/__init__.py
src/utils/data_utils.py
src/utils/file_utils.py
src/utils/utils.py
src/utils/validation_utils.py
src/visualiser/__init__.py
src/visualiser/utils.py
src/visualiser/visualiser.py
src/visualiser/visualiser_cmd.py
tests/__init__.py
tests/test_cleaner.py
tests/test_fileHandler.py
tests/test_reporter.py
tests/test_transformer.py
tests/test_visualiser.py
TidyDataCLI-0.2.8.dist-info/LICENSE
TidyDataCLI-0.2.8.dist-info/METADATA
TidyDataCLI-0.2.8.dist-info/WHEEL
TidyDataCLI-0.2.8.dist-info/entry_points.txt
TidyDataCLI-0.2.8.dist-info/top_level.txt
TidyDataCLI-0.2.8.dist-info/RECORD
