Metadata-Version: 2.1
Name: TidyDataCLI
Version: 0.2.8
Summary: A CLI tool to automate cleaning, transformation and visualisation of Excel/CSV data.
Home-page: https://github.com/Siam3h/TidyDataCLI.git
Author: Philbert Siama
Author-email: siamaphilbert@outlook.com
Classifier: Programming Language :: Python :: 3
Classifier: License :: OSI Approved :: MIT License
Classifier: Operating System :: OS Independent
Requires-Python: >3.9
License-File: LICENSE
Requires-Dist: pandas ==2.2.2
Requires-Dist: matplotlib ==3.9.2
Requires-Dist: openpyxl ==3.1.5
Requires-Dist: build ==1.2.1
Requires-Dist: certifi ==2024.7.4
Requires-Dist: chardet ==5.2.0
Requires-Dist: charset-normalizer ==3.3.2
Requires-Dist: colorama ==0.4.6
Requires-Dist: contourpy ==1.3.0
Requires-Dist: cycler ==0.12.1
Requires-Dist: docutils ==0.21.2
Requires-Dist: et-xmlfile ==1.1.0
Requires-Dist: fonttools ==4.53.1
Requires-Dist: idna ==3.7
Requires-Dist: importlib-metadata ==8.4.0
Requires-Dist: jaraco.classes ==3.4.0
Requires-Dist: jaraco.context ==6.0.1
Requires-Dist: jaraco.functools ==4.0.2
Requires-Dist: kaleido ==0.2.1
Requires-Dist: keyring ==25.3.0
Requires-Dist: kiwisolver ==1.4.5
Requires-Dist: markdown-it-py ==3.0.0
Requires-Dist: mdurl ==0.1.2
Requires-Dist: more-itertools ==10.4.0
Requires-Dist: nh3 ==0.2.18
Requires-Dist: numpy ==2.0.1
Requires-Dist: packaging ==24.1
Requires-Dist: pillow ==10.4.0
Requires-Dist: pkginfo ==1.10.0
Requires-Dist: plotly ==5.24.0
Requires-Dist: Pygments ==2.18.0
Requires-Dist: pyparsing ==3.1.4
Requires-Dist: pyproject-hooks ==1.1.0
Requires-Dist: python-dateutil ==2.9.0.post0
Requires-Dist: pytz ==2024.1
Requires-Dist: pywin32-ctypes ==0.2.3
Requires-Dist: readme-renderer ==44.0
Requires-Dist: reportlab ==4.2.2
Requires-Dist: requests ==2.32.3
Requires-Dist: requests-toolbelt ==1.0.0
Requires-Dist: rfc3986 ==2.0.0
Requires-Dist: rich ==13.7.1
Requires-Dist: seaborn ==0.13.2
Requires-Dist: setuptools ==73.0.1
Requires-Dist: six ==1.16.0
Requires-Dist: tenacity ==9.0.0
Requires-Dist: twine ==5.1.1
Requires-Dist: tzdata ==2024.1
Requires-Dist: urllib3 ==2.2.2
Requires-Dist: wheel ==0.44.0
Requires-Dist: wordcloud ==1.9.3
Requires-Dist: zipp ==3.20.0
